treesa_ai/__init__.py
treesa_ai/core.py
treesa_ai/version.py
treesa_ai_helper-0.0.9.dist-info/licenses/LICENSE
treesa_ai_helper-0.0.9.dist-info/METADATA
treesa_ai_helper-0.0.9.dist-info/WHEEL
treesa_ai_helper-0.0.9.dist-info/top_level.txt
treesa_ai_helper-0.0.9.dist-info/RECORD
