Metadata-Version: 2.4
Name: treesa-ai-helper
Version: 0.0.9
Summary: An AI helper library for generating text responses
Author-email: Treesa Jose <2treesajo@gmail.com>
Project-URL: Homepage, https://pypi.org/project/treesa-ai-helper/
Requires-Python: >=3.8
License-File: LICENSE
Requires-Dist: groq>=0.4.0
Requires-Dist: python-dotenv
Dynamic: license-file
